[
  {
    "id": "plasma_reaper",
    "name": "Plasma Reaper",
    "type": "Weapon",
    "rarity": "epic",
    "energy_cost": 4,
    "attack": 13,
    "defense": 0,
    "effect_text": "Priority Fire. Overclock. Critical Strike. Deal 13 damage.",
    "keywords": [
      "priority_fire",
      "overclock",
      "critical_strike"
    ],
    "flavor_text": "The reaper. The gun the old squadron never liked to clean. Kept firing regardless.",
    "archetype": "combo",
    "subsystem_target": null,
    "escalation": false,
    "dual_identity": false,
    "cargo": false
  },
  {
    "id": "chrono_cannon",
    "name": "Chrono Cannon",
    "type": "Weapon",
    "rarity": "epic",
    "energy_cost": 4,
    "attack": 12,
    "defense": 0,
    "effect_text": "Phase Drive. Quick Strike. Priority Fire. Deal 12 damage first.",
    "keywords": [
      "phase_drive",
      "quick_strike",
      "priority_fire"
    ],
    "flavor_text": "Fires through last week and into next week. Both weeks remember the round.",
    "archetype": "aggro",
    "subsystem_target": null,
    "escalation": false,
    "dual_identity": false,
    "cargo": false
  },
  {
    "id": "twin_fusion",
    "name": "Twin Fusion",
    "type": "Weapon",
    "rarity": "epic",
    "energy_cost": 4,
    "attack": 13,
    "defense": 0,
    "effect_text": "Alpha Strike. Linked Fire. Priority Fire. Deal 6 damage twice; second +2.",
    "keywords": [
      "alpha_strike",
      "linked_fire",
      "priority_fire"
    ],
    "flavor_text": "Two cores firing in sync. The sync is the hard part. Cores are not subtle.",
    "archetype": "aggro",
    "subsystem_target": null,
    "escalation": false,
    "dual_identity": false,
    "cargo": false
  },
  {
    "id": "arc_storm",
    "name": "Arc Storm",
    "type": "Weapon",
    "rarity": "epic",
    "energy_cost": 4,
    "attack": 12,
    "defense": 0,
    "effect_text": "Breach Cascade. Chain Catalyst. Overclock. Deal 12; adjacent 4; next card +2.",
    "keywords": [
      "breach_cascade",
      "chain_catalyst",
      "overclock"
    ],
    "flavor_text": "A storm that hops ship to ship. Each hop polite, measured, bringing its own receipt.",
    "archetype": "combo",
    "subsystem_target": null,
    "escalation": false,
    "dual_identity": false,
    "cargo": false
  },
  {
    "id": "shadowbeam",
    "name": "Shadowbeam",
    "type": "Weapon",
    "rarity": "epic",
    "energy_cost": 5,
    "attack": 16,
    "defense": 0,
    "effect_text": "Gain Stealth. Phase Drive. Critical Strike. Deal 16 damage, unseen.",
    "keywords": [
      "gain_stealth",
      "phase_drive",
      "critical_strike"
    ],
    "flavor_text": "The gun the fleet refuses to itemize. The shipyard welds it in anyway.",
    "archetype": "control",
    "subsystem_target": null,
    "escalation": false,
    "dual_identity": false,
    "cargo": false
  },
  {
    "id": "quad_salvo",
    "name": "Quad Salvo",
    "type": "Weapon",
    "rarity": "epic",
    "energy_cost": 5,
    "attack": 16,
    "defense": 0,
    "effect_text": "Rapid Launch. Alpha Strike. Priority Fire. Deal 8 damage twice, first.",
    "keywords": [
      "rapid_launch",
      "alpha_strike",
      "priority_fire"
    ],
    "flavor_text": "Four tubes empty in the same beat. The ship spends the beat smiling quietly.",
    "archetype": "midrange",
    "subsystem_target": null,
    "escalation": false,
    "dual_identity": false,
    "cargo": false
  },
  {
    "id": "ion_destroyer",
    "name": "Ion Destroyer",
    "type": "Weapon",
    "rarity": "epic",
    "energy_cost": 5,
    "attack": 16,
    "defense": 0,
    "effect_text": "Critical Strike. Radiation Leak. Priority Fire. Deal 16; 4 radiation over 3 turns.",
    "keywords": [
      "critical_strike",
      "radiation_leak",
      "priority_fire"
    ],
    "flavor_text": "A quiet gun. A loud afterword. The enemy learns the afterword from the inside.",
    "archetype": "control",
    "subsystem_target": null,
    "escalation": false,
    "dual_identity": false,
    "cargo": false
  },
  {
    "id": "siege_spike",
    "name": "Siege Spike",
    "type": "Weapon",
    "rarity": "epic",
    "energy_cost": 5,
    "attack": 16,
    "defense": 0,
    "effect_text": "Cold Boot 1. Critical Strike. Overflow Fire. Deal 16; excess hits ship.",
    "keywords": [
      "cold_boot",
      "critical_strike",
      "overflow_fire"
    ],
    "flavor_text": "Arms slowly. Arrives politely. Leaves nothing the engineers want itemized.",
    "archetype": "midrange",
    "subsystem_target": null,
    "escalation": false,
    "dual_identity": false,
    "cargo": false
  },
  {
    "id": "nova_cannon",
    "name": "Nova Cannon",
    "type": "Weapon",
    "rarity": "epic",
    "energy_cost": 5,
    "attack": 16,
    "defense": 0,
    "effect_text": "Breach Cascade. Overflow Fire. Radiation Leak. Deal 16; adjacent 5; 3 radiation.",
    "keywords": [
      "breach_cascade",
      "overflow_fire",
      "radiation_leak"
    ],
    "flavor_text": "A bottled star. Uncorked on a schedule. Drinks the room dry before anyone notices.",
    "archetype": "aggro",
    "subsystem_target": null,
    "escalation": false,
    "dual_identity": false,
    "cargo": false
  },
  {
    "id": "reaper_lance",
    "name": "Reaper Lance",
    "type": "Weapon",
    "rarity": "epic",
    "energy_cost": 6,
    "attack": 20,
    "defense": 0,
    "effect_text": "Priority Fire. Critical Strike. Overclock. Deal 20 damage, first.",
    "keywords": [
      "priority_fire",
      "critical_strike",
      "overclock"
    ],
    "flavor_text": "The gun in the admiral's office. The admiral had it mounted before retirement.",
    "archetype": "combo",
    "subsystem_target": null,
    "escalation": false,
    "dual_identity": false,
    "cargo": false
  },
  {
    "id": "void_breaker",
    "name": "Void Breaker",
    "type": "Weapon",
    "rarity": "epic",
    "energy_cost": 6,
    "attack": 20,
    "defense": 0,
    "effect_text": "Phase Drive. Overflow Fire. Radiation Leak. Deal 20; excess to ship; 4 radiation.",
    "keywords": [
      "phase_drive",
      "overflow_fire",
      "radiation_leak"
    ],
    "flavor_text": "Breaks something that does not want to be broken. The fleet writes up the paperwork.",
    "archetype": "control",
    "subsystem_target": null,
    "escalation": false,
    "dual_identity": false,
    "cargo": false
  },
  {
    "id": "apocalypse_gun",
    "name": "Apocalypse Gun",
    "type": "Weapon",
    "rarity": "epic",
    "energy_cost": 6,
    "attack": 20,
    "defense": 0,
    "effect_text": "Breach Cascade. Alpha Strike. Priority Fire. Deal 10 twice; adjacent 4.",
    "keywords": [
      "breach_cascade",
      "alpha_strike",
      "priority_fire"
    ],
    "flavor_text": "Not the worst weapon on the manifest. Still the loudest one anybody voluntarily checks out.",
    "archetype": "combo",
    "subsystem_target": null,
    "escalation": false,
    "dual_identity": false,
    "cargo": false
  },
  {
    "id": "siege_master",
    "name": "Siege Master",
    "type": "Weapon",
    "rarity": "epic",
    "energy_cost": 6,
    "attack": 20,
    "defense": 0,
    "effect_text": "Cold Boot 1. Cascading Power. Critical Strike. Deal 20 damage; +1 per non-unit card.",
    "keywords": [
      "cold_boot",
      "cascading_power",
      "critical_strike"
    ],
    "flavor_text": "Patient gun. Patient pilot. Patient enemy, at least until the third minute.",
    "archetype": "midrange",
    "subsystem_target": null,
    "escalation": false,
    "dual_identity": false,
    "cargo": false
  },
  {
    "id": "hyper_cannon",
    "name": "Hyper Cannon",
    "type": "Weapon",
    "rarity": "epic",
    "energy_cost": 7,
    "attack": 24,
    "defense": 0,
    "effect_text": "Priority Fire. Alpha Strike. Critical Strike. Deal 12 twice, first.",
    "keywords": [
      "priority_fire",
      "alpha_strike",
      "critical_strike"
    ],
    "flavor_text": "Designed to make test pilots laugh nervously. The pilots still ask for it.",
    "archetype": "combo",
    "subsystem_target": null,
    "escalation": false,
    "dual_identity": false,
    "cargo": false
  },
  {
    "id": "void_storm",
    "name": "Void Storm",
    "type": "Weapon",
    "rarity": "epic",
    "energy_cost": 7,
    "attack": 24,
    "defense": 0,
    "effect_text": "Breach Cascade. Radiation Leak. Overflow Fire. Deal 24; adjacent 6; 5 radiation.",
    "keywords": [
      "breach_cascade",
      "radiation_leak",
      "overflow_fire"
    ],
    "flavor_text": "Happens on the sensor suite, not the eye. The sensor suite lies down afterwards.",
    "archetype": "aggro",
    "subsystem_target": null,
    "escalation": false,
    "dual_identity": false,
    "cargo": false
  },
  {
    "id": "stellar_spike",
    "name": "Stellar Spike",
    "type": "Weapon",
    "rarity": "epic",
    "energy_cost": 7,
    "attack": 24,
    "defense": 0,
    "effect_text": "Critical Strike. Phase Drive. Overflow Fire. Deal 24 damage; bypasses most blockers.",
    "keywords": [
      "critical_strike",
      "phase_drive",
      "overflow_fire"
    ],
    "flavor_text": "Born in a shipyard that no longer exists. Still listed on its manifest.",
    "archetype": "control",
    "subsystem_target": null,
    "escalation": false,
    "dual_identity": false,
    "cargo": false
  },
  {
    "id": "planetary_cannon",
    "name": "Planetary Cannon",
    "type": "Weapon",
    "rarity": "epic",
    "energy_cost": 8,
    "attack": 28,
    "defense": 0,
    "effect_text": "Priority Fire. Overflow Fire. Radiation Leak. Deal 28; excess to ship; 5 radiation.",
    "keywords": [
      "priority_fire",
      "overflow_fire",
      "radiation_leak"
    ],
    "flavor_text": "The gun treaty writers argued about for six months. The enemy gets the summary.",
    "archetype": "midrange",
    "subsystem_target": null,
    "escalation": false,
    "dual_identity": false,
    "cargo": false
  },
  {
    "id": "sky_reaver",
    "name": "Sky Reaver",
    "type": "Drone",
    "rarity": "epic",
    "energy_cost": 4,
    "attack": 7,
    "defense": 5,
    "effect_text": "Rapid Launch. Skyward Maneuver. Priority Fire.",
    "keywords": [
      "rapid_launch",
      "skyward_maneuver",
      "priority_fire"
    ],
    "flavor_text": "Climbs past the ceiling of the fight. Picks its angle down. Picks its target personally.",
    "archetype": "midrange",
    "subsystem_target": null,
    "escalation": false,
    "dual_identity": false,
    "cargo": false
  },
  {
    "id": "phantom_elite",
    "name": "Phantom Elite",
    "type": "Drone",
    "rarity": "epic",
    "energy_cost": 4,
    "attack": 6,
    "defense": 6,
    "effect_text": "Gain Stealth. Cloaked Entry. Phase Drive.",
    "keywords": [
      "gain_stealth",
      "cloaked_entry",
      "phase_drive"
    ],
    "flavor_text": "Never on the sensor. Never in the manifest. Never the first thing the enemy remembers.",
    "archetype": "utility",
    "subsystem_target": null,
    "escalation": false,
    "dual_identity": false,
    "cargo": false
  },
  {
    "id": "terror_bomber",
    "name": "Terror Bomber",
    "type": "Drone",
    "rarity": "epic",
    "energy_cost": 4,
    "attack": 8,
    "defense": 5,
    "effect_text": "Critical Breach: deal 6 damage. Hot Deploy. Rapid Launch.",
    "keywords": [
      "critical_breach",
      "hot_deploy",
      "rapid_launch"
    ],
    "flavor_text": "Carries ordnance the fleet no longer lists. Delivers it before anyone can read the manifest.",
    "archetype": "midrange",
    "subsystem_target": null,
    "escalation": false,
    "dual_identity": false,
    "cargo": false
  },
  {
    "id": "guardian_elite",
    "name": "Guardian Elite",
    "type": "Drone",
    "rarity": "epic",
    "energy_cost": 5,
    "attack": 5,
    "defense": 12,
    "effect_text": "Interceptor. Reinforced Hull. Auto-Repair 2.",
    "keywords": [
      "interceptor",
      "reinforced_hull",
      "auto_repair"
    ],
    "flavor_text": "Stood at the last gate of the last port. Still standing. Still quietly collecting thanks.",
    "archetype": "midrange",
    "subsystem_target": null,
    "escalation": false,
    "dual_identity": false,
    "cargo": false
  },
  {
    "id": "bomber_overlord",
    "name": "Bomber Overlord",
    "type": "Drone",
    "rarity": "epic",
    "energy_cost": 5,
    "attack": 10,
    "defense": 6,
    "effect_text": "Rapid Launch. Critical Breach: deal 8 damage. Alpha Strike.",
    "keywords": [
      "rapid_launch",
      "critical_breach",
      "alpha_strike"
    ],
    "flavor_text": "Runs every sortie twice. Lands once. Drops a long note into the plating.",
    "archetype": "midrange",
    "subsystem_target": null,
    "escalation": false,
    "dual_identity": false,
    "cargo": false
  },
  {
    "id": "phantom_siege",
    "name": "Phantom Siege",
    "type": "Drone",
    "rarity": "epic",
    "energy_cost": 5,
    "attack": 9,
    "defense": 8,
    "effect_text": "Gain Stealth. Critical Strike. Phase Drive.",
    "keywords": [
      "gain_stealth",
      "critical_strike",
      "phase_drive"
    ],
    "flavor_text": "Arrives from nowhere. Leaves through the same nowhere. The enemy files a strongly worded nowhere.",
    "archetype": "control",
    "subsystem_target": null,
    "escalation": false,
    "dual_identity": false,
    "cargo": false
  },
  {
    "id": "warchief",
    "name": "Warchief",
    "type": "Drone",
    "rarity": "epic",
    "energy_cost": 5,
    "attack": 8,
    "defense": 9,
    "effect_text": "Battle Hardened. Priority Fire. Outrider.",
    "keywords": [
      "battle_hardened",
      "priority_fire",
      "outrider"
    ],
    "flavor_text": "Takes the front. Holds the front. Rewrites the definition of the front, casually.",
    "archetype": "midrange",
    "subsystem_target": null,
    "escalation": false,
    "dual_identity": false,
    "cargo": false
  },
  {
    "id": "siege_overlord",
    "name": "Siege Overlord",
    "type": "Drone",
    "rarity": "epic",
    "energy_cost": 6,
    "attack": 12,
    "defense": 8,
    "effect_text": "Priority Fire. Cold Boot 1. Alpha Strike.",
    "keywords": [
      "priority_fire",
      "cold_boot",
      "alpha_strike"
    ],
    "flavor_text": "Warms up loud. Fires louder. The siege lasts exactly as the overlord intends.",
    "archetype": "midrange",
    "subsystem_target": null,
    "escalation": false,
    "dual_identity": false,
    "cargo": false
  },
  {
    "id": "phantom_overlord",
    "name": "Phantom Overlord",
    "type": "Drone",
    "rarity": "epic",
    "energy_cost": 6,
    "attack": 10,
    "defense": 10,
    "effect_text": "Gain Stealth. Cloaked Entry. Critical Strike.",
    "keywords": [
      "gain_stealth",
      "cloaked_entry",
      "critical_strike"
    ],
    "flavor_text": "Does the work of three invisible drones. The paperwork remains efficient.",
    "archetype": "utility",
    "subsystem_target": null,
    "escalation": false,
    "dual_identity": false,
    "cargo": false
  },
  {
    "id": "guardian_overlord",
    "name": "Guardian Overlord",
    "type": "Drone",
    "rarity": "epic",
    "energy_cost": 6,
    "attack": 6,
    "defense": 15,
    "effect_text": "Interceptor. Reinforced Hull. Emergency Reboot.",
    "keywords": [
      "interceptor",
      "reinforced_hull",
      "emergency_reboot"
    ],
    "flavor_text": "Stands. Falls. Stands again. The morale officer has a hymn for it, quietly.",
    "archetype": "midrange",
    "subsystem_target": null,
    "escalation": false,
    "dual_identity": false,
    "cargo": false
  },
  {
    "id": "fleet_admiral",
    "name": "Fleet Admiral",
    "type": "Drone",
    "rarity": "epic",
    "energy_cost": 7,
    "attack": 13,
    "defense": 13,
    "effect_text": "Priority Fire. Alpha Strike. Rapid Launch.",
    "keywords": [
      "priority_fire",
      "alpha_strike",
      "rapid_launch"
    ],
    "flavor_text": "Commands the wing from the middle. Never loses a wingman without a reason.",
    "archetype": "midrange",
    "subsystem_target": null,
    "escalation": false,
    "dual_identity": false,
    "cargo": false
  },
  {
    "id": "capital_terror",
    "name": "Capital Terror",
    "type": "Drone",
    "rarity": "epic",
    "energy_cost": 7,
    "attack": 15,
    "defense": 11,
    "effect_text": "Rapid Launch. Critical Breach: deal 10. Cold Boot 1.",
    "keywords": [
      "rapid_launch",
      "critical_breach",
      "cold_boot"
    ],
    "flavor_text": "Warms up loud. Arrives louder. Leaves quiet, because there is not much left that moves.",
    "archetype": "midrange",
    "subsystem_target": null,
    "escalation": false,
    "dual_identity": false,
    "cargo": false
  },
  {
    "id": "apex_destroyer",
    "name": "Apex Destroyer",
    "type": "Drone",
    "rarity": "epic",
    "energy_cost": 8,
    "attack": 16,
    "defense": 14,
    "effect_text": "Priority Fire. Alpha Strike. Critical Strike.",
    "keywords": [
      "priority_fire",
      "alpha_strike",
      "critical_strike"
    ],
    "flavor_text": "The last name on the roster. The first name on the enemy's complaint letter.",
    "archetype": "aggro",
    "subsystem_target": null,
    "escalation": false,
    "dual_identity": false,
    "cargo": false
  },
  {
    "id": "prime_command",
    "name": "Prime Command",
    "type": "AI Routine",
    "rarity": "epic",
    "energy_cost": 4,
    "attack": 0,
    "defense": 13,
    "effect_text": "Persistent Field. Priority Fire. Overclock. Chain Catalyst.",
    "keywords": [
      "persistent_field",
      "priority_fire",
      "overclock",
      "chain_catalyst"
    ],
    "flavor_text": "The command line the fleet admiral keeps on autologin. Nobody audits it anymore.",
    "archetype": "combo",
    "subsystem_target": null,
    "escalation": false,
    "dual_identity": false,
    "cargo": false
  },
  {
    "id": "master_scanner_e",
    "name": "Master Scanner (Epic)",
    "type": "AI Routine",
    "rarity": "epic",
    "energy_cost": 4,
    "attack": 0,
    "defense": 12,
    "effect_text": "Persistent Field. Probe 2 each turn. Deep Scan. Tactical Draw.",
    "keywords": [
      "persistent_field",
      "probe",
      "deep_scan",
      "tactical_draw"
    ],
    "flavor_text": "Reads the deck above. Reads the deck below. Writes the pilot's briefing compiled.",
    "archetype": "utility",
    "subsystem_target": null,
    "escalation": false,
    "dual_identity": false,
    "cargo": false
  },
  {
    "id": "prime_fortress",
    "name": "Prime Fortress",
    "type": "AI Routine",
    "rarity": "epic",
    "energy_cost": 4,
    "attack": 0,
    "defense": 14,
    "effect_text": "Persistent Field. Interceptor. Reinforced Hull. Ablative Plating.",
    "keywords": [
      "persistent_field",
      "interceptor",
      "reinforced_hull",
      "ablative_plating"
    ],
    "flavor_text": "Stands every wall at attention. Every wall listens. Every wall outlasts the argument.",
    "archetype": "midrange",
    "subsystem_target": null,
    "escalation": false,
    "dual_identity": false,
    "cargo": false
  },
  {
    "id": "master_uplink",
    "name": "Master Uplink",
    "type": "AI Routine",
    "rarity": "epic",
    "energy_cost": 5,
    "attack": 0,
    "defense": 16,
    "effect_text": "Persistent Field. Cascading Power. Linked Fire. Chain Catalyst.",
    "keywords": [
      "persistent_field",
      "cascading_power",
      "linked_fire",
      "chain_catalyst"
    ],
    "flavor_text": "Every gun in the fleet on one line, on the same heartbeat. The heartbeat wins.",
    "archetype": "midrange",
    "subsystem_target": null,
    "escalation": false,
    "dual_identity": false,
    "cargo": false
  },
  {
    "id": "prime_shield_e",
    "name": "Prime Shield (Epic)",
    "type": "AI Routine",
    "rarity": "epic",
    "energy_cost": 5,
    "attack": 0,
    "defense": 17,
    "effect_text": "Persistent Field. Auto-Repair 2. Emergency Reboot. Adaptive Learning.",
    "keywords": [
      "persistent_field",
      "auto_repair",
      "emergency_reboot",
      "adaptive_learning"
    ],
    "flavor_text": "Every bad afternoon gets the same quiet treatment. Every good afternoon still thanks it.",
    "archetype": "ramp",
    "subsystem_target": null,
    "escalation": false,
    "dual_identity": false,
    "cargo": false
  },
  {
    "id": "ghost_overmind",
    "name": "Ghost Overmind",
    "type": "AI Routine",
    "rarity": "epic",
    "energy_cost": 5,
    "attack": 0,
    "defense": 16,
    "effect_text": "Persistent Field. Gain Stealth. Cloaked Entry. Phase Drive.",
    "keywords": [
      "persistent_field",
      "gain_stealth",
      "cloaked_entry",
      "phase_drive"
    ],
    "flavor_text": "Writes the fleet out of the enemy sensor. Keeps the fleet written out indefinitely.",
    "archetype": "utility",
    "subsystem_target": null,
    "escalation": false,
    "dual_identity": false,
    "cargo": false
  },
  {
    "id": "commander_elite",
    "name": "Commander Elite",
    "type": "AI Routine",
    "rarity": "epic",
    "energy_cost": 5,
    "attack": 0,
    "defense": 16,
    "effect_text": "Persistent Field. Priority Fire. Rapid Launch. Critical Strike.",
    "keywords": [
      "persistent_field",
      "priority_fire",
      "rapid_launch",
      "critical_strike"
    ],
    "flavor_text": "The voice on every comm at once. Every pilot listens. Every pilot knows the drill.",
    "archetype": "aggro",
    "subsystem_target": null,
    "escalation": false,
    "dual_identity": false,
    "cargo": false
  },
  {
    "id": "supreme_heat",
    "name": "Supreme Heat",
    "type": "AI Routine",
    "rarity": "epic",
    "energy_cost": 6,
    "attack": 0,
    "defense": 20,
    "effect_text": "Persistent Field. Overclock. Efficiency Protocol. Cascading Power.",
    "keywords": [
      "persistent_field",
      "overclock",
      "efficiency_protocol",
      "cascading_power"
    ],
    "flavor_text": "The reactor runs past the gauge. The gauge apologizes. The fleet keeps its lead.",
    "archetype": "combo",
    "subsystem_target": null,
    "escalation": false,
    "dual_identity": false,
    "cargo": false
  },
  {
    "id": "prime_hunter",
    "name": "Prime Hunter",
    "type": "AI Routine",
    "rarity": "epic",
    "energy_cost": 6,
    "attack": 0,
    "defense": 20,
    "effect_text": "Persistent Field. Tracking Lock. Priority Fire. Critical Strike.",
    "keywords": [
      "persistent_field",
      "tracking_lock",
      "priority_fire",
      "critical_strike"
    ],
    "flavor_text": "Writes the target's name on every instrument panel in the fleet. Target learns late.",
    "archetype": "combo",
    "subsystem_target": null,
    "escalation": false,
    "dual_identity": false,
    "cargo": false
  },
  {
    "id": "apex_master",
    "name": "Apex Master",
    "type": "AI Routine",
    "rarity": "epic",
    "energy_cost": 6,
    "attack": 0,
    "defense": 21,
    "effect_text": "Persistent Field. Adaptive Learning. Efficiency Protocol. Chain Catalyst.",
    "keywords": [
      "persistent_field",
      "adaptive_learning",
      "efficiency_protocol",
      "chain_catalyst"
    ],
    "flavor_text": "Learns from every fight. Remembers every fight. The fights arrive easier and easier.",
    "archetype": "ramp",
    "subsystem_target": null,
    "escalation": false,
    "dual_identity": false,
    "cargo": false
  },
  {
    "id": "ultimate_commander",
    "name": "Ultimate Commander",
    "type": "AI Routine",
    "rarity": "epic",
    "energy_cost": 7,
    "attack": 0,
    "defense": 25,
    "effect_text": "Persistent Field. Priority Fire. Rapid Launch. Alpha Strike.",
    "keywords": [
      "persistent_field",
      "priority_fire",
      "rapid_launch",
      "alpha_strike"
    ],
    "flavor_text": "Commands the fleet in one breath. The fleet obeys on the same breath, loudly.",
    "archetype": "aggro",
    "subsystem_target": null,
    "escalation": false,
    "dual_identity": false,
    "cargo": false
  },
  {
    "id": "prime_overmind",
    "name": "Prime Overmind",
    "type": "AI Routine",
    "rarity": "epic",
    "energy_cost": 7,
    "attack": 0,
    "defense": 24,
    "effect_text": "Persistent Field. Cascading Power. Chain Catalyst. Linked Fire.",
    "keywords": [
      "persistent_field",
      "cascading_power",
      "chain_catalyst",
      "linked_fire"
    ],
    "flavor_text": "Every gun reads the same page at the same moment. They close the book together.",
    "archetype": "combo",
    "subsystem_target": null,
    "escalation": false,
    "dual_identity": false,
    "cargo": false
  },
  {
    "id": "grand_supreme",
    "name": "Grand Supreme",
    "type": "AI Routine",
    "rarity": "epic",
    "energy_cost": 8,
    "attack": 0,
    "defense": 30,
    "effect_text": "Persistent Field. Priority Fire. Overclock. Cascading Power.",
    "keywords": [
      "persistent_field",
      "priority_fire",
      "overclock",
      "cascading_power"
    ],
    "flavor_text": "The program the fleet's flagship refuses to discuss. The flagship runs it anyway.",
    "archetype": "combo",
    "subsystem_target": null,
    "escalation": false,
    "dual_identity": false,
    "cargo": false
  },
  {
    "id": "master_fortress_e",
    "name": "Master Fortress (Epic)",
    "type": "Defense",
    "rarity": "epic",
    "energy_cost": 4,
    "attack": 0,
    "defense": 14,
    "effect_text": "Interceptor. Reinforced Hull. Ablative Plating. Auto-Repair.",
    "keywords": [
      "interceptor",
      "reinforced_hull",
      "ablative_plating",
      "auto_repair"
    ],
    "flavor_text": "The pattern every fortress after it tried to imitate. None quite got there.",
    "archetype": "midrange",
    "subsystem_target": null,
    "escalation": false,
    "dual_identity": false,
    "cargo": false
  },
  {
    "id": "aegis_lord",
    "name": "Aegis Lord",
    "type": "Defense",
    "rarity": "epic",
    "energy_cost": 4,
    "attack": 0,
    "defense": 14,
    "effect_text": "Ablative Plating 2. Emergency Reboot. Reinforced Hull. System Shielding.",
    "keywords": [
      "ablative_plating",
      "emergency_reboot",
      "reinforced_hull",
      "system_shielding"
    ],
    "flavor_text": "Four patterns welded into one frame. Each pattern trusts the other three completely.",
    "archetype": "midrange",
    "subsystem_target": null,
    "escalation": false,
    "dual_identity": false,
    "cargo": false
  },
  {
    "id": "phase_master",
    "name": "Phase Master",
    "type": "Defense",
    "rarity": "epic",
    "energy_cost": 5,
    "attack": 0,
    "defense": 16,
    "effect_text": "Phase Drive. Gain Stealth. Reinforced Hull. Evade 40%.",
    "keywords": [
      "phase_drive",
      "gain_stealth",
      "reinforced_hull",
      "evade"
    ],
    "flavor_text": "Half the wall is elsewhere. Elsewhere is where most enemy rounds end up.",
    "archetype": "control",
    "subsystem_target": null,
    "escalation": false,
    "dual_identity": false,
    "cargo": false
  },
  {
    "id": "apex_barrier",
    "name": "Apex Barrier",
    "type": "Defense",
    "rarity": "epic",
    "energy_cost": 5,
    "attack": 0,
    "defense": 17,
    "effect_text": "Interceptor. Ablative Plating 2. Auto-Repair 2. Emergency Reboot.",
    "keywords": [
      "interceptor",
      "ablative_plating",
      "auto_repair",
      "emergency_reboot"
    ],
    "flavor_text": "Takes the hit. Knits the seam. Repeats. The fleet reinstalls it on every hull.",
    "archetype": "ramp",
    "subsystem_target": null,
    "escalation": false,
    "dual_identity": false,
    "cargo": false
  },
  {
    "id": "stealth_master",
    "name": "Stealth Master",
    "type": "Defense",
    "rarity": "epic",
    "energy_cost": 5,
    "attack": 0,
    "defense": 17,
    "effect_text": "Gain Stealth. Cloaked Entry. Evade 40%. Reinforced Hull.",
    "keywords": [
      "gain_stealth",
      "cloaked_entry",
      "evade",
      "reinforced_hull"
    ],
    "flavor_text": "Never on the map. Never in the briefing. Never the first thing the enemy remembers.",
    "archetype": "control",
    "subsystem_target": null,
    "escalation": false,
    "dual_identity": false,
    "cargo": false
  },
  {
    "id": "grand_fortress_e",
    "name": "Grand Fortress (Epic)",
    "type": "Defense",
    "rarity": "epic",
    "energy_cost": 5,
    "attack": 2,
    "defense": 16,
    "effect_text": "Interceptor. Reinforced Hull. Battle Hardened. Gains power from damage taken.",
    "keywords": [
      "interceptor",
      "reinforced_hull",
      "battle_hardened"
    ],
    "flavor_text": "Takes hits until hits feed it. Then the hits look small. Then nothing looks small.",
    "archetype": "midrange",
    "subsystem_target": null,
    "escalation": false,
    "dual_identity": false,
    "cargo": false
  },
  {
    "id": "titanic_lord",
    "name": "Titanic Lord",
    "type": "Defense",
    "rarity": "epic",
    "energy_cost": 6,
    "attack": 0,
    "defense": 21,
    "effect_text": "Ablative Plating 3. Reinforced Hull. Emergency Reboot. Auto-Repair 2.",
    "keywords": [
      "ablative_plating",
      "reinforced_hull",
      "emergency_reboot",
      "auto_repair"
    ],
    "flavor_text": "Every mission log lists this one as the thing that came home. Every time.",
    "archetype": "ramp",
    "subsystem_target": null,
    "escalation": false,
    "dual_identity": false,
    "cargo": false
  },
  {
    "id": "fortress_supreme",
    "name": "Fortress Supreme",
    "type": "Defense",
    "rarity": "epic",
    "energy_cost": 6,
    "attack": 3,
    "defense": 20,
    "effect_text": "Interceptor. Reinforced Hull. Ablative Plating 2. Auto-Repair 2.",
    "keywords": [
      "interceptor",
      "reinforced_hull",
      "ablative_plating",
      "auto_repair"
    ],
    "flavor_text": "The wall the admiral stands behind during every briefing. The wall the admiral trusts.",
    "archetype": "midrange",
    "subsystem_target": null,
    "escalation": false,
    "dual_identity": false,
    "cargo": false
  },
  {
    "id": "phase_supreme",
    "name": "Phase Supreme",
    "type": "Defense",
    "rarity": "epic",
    "energy_cost": 6,
    "attack": 0,
    "defense": 22,
    "effect_text": "Phase Drive. Reinforced Hull. Emergency Reboot.",
    "keywords": [
      "phase_drive",
      "reinforced_hull",
      "emergency_reboot"
    ],
    "flavor_text": "Half the wall argues with the next universe over. Both halves refuse to fall together.",
    "archetype": "control",
    "subsystem_target": null,
    "escalation": false,
    "dual_identity": false,
    "cargo": false
  },
  {
    "id": "aegis_supreme",
    "name": "Aegis Supreme",
    "type": "Defense",
    "rarity": "epic",
    "energy_cost": 7,
    "attack": 0,
    "defense": 25,
    "effect_text": "Ablative Plating 4. Auto-Repair 3. Emergency Reboot. Reinforced Hull.",
    "keywords": [
      "ablative_plating",
      "auto_repair",
      "emergency_reboot",
      "reinforced_hull"
    ],
    "flavor_text": "Four patterns, four patiences, one promise: this hull stays where the pilot parked it.",
    "archetype": "ramp",
    "subsystem_target": null,
    "escalation": false,
    "dual_identity": false,
    "cargo": false
  },
  {
    "id": "citadel_lord",
    "name": "Citadel Lord",
    "type": "Defense",
    "rarity": "epic",
    "energy_cost": 7,
    "attack": 3,
    "defense": 24,
    "effect_text": "Interceptor. Reinforced Hull. Auto-Repair 2.",
    "keywords": [
      "interceptor",
      "reinforced_hull",
      "auto_repair"
    ],
    "flavor_text": "Stands at the gate. Has stood there since before the gate had a name.",
    "archetype": "midrange",
    "subsystem_target": null,
    "escalation": false,
    "dual_identity": false,
    "cargo": false
  },
  {
    "id": "primordial_bastion",
    "name": "Primordial Bastion",
    "type": "Defense",
    "rarity": "epic",
    "energy_cost": 8,
    "attack": 0,
    "defense": 30,
    "effect_text": "Interceptor. Reinforced Hull. Ablative Plating 3. Emergency Reboot.",
    "keywords": [
      "interceptor",
      "reinforced_hull",
      "ablative_plating",
      "emergency_reboot"
    ],
    "flavor_text": "Older than the fleet. Older than the enemy fleet. Patient as both fleets combined.",
    "archetype": "midrange",
    "subsystem_target": null,
    "escalation": false,
    "dual_identity": false,
    "cargo": false
  },
  {
    "id": "master_warhead_e",
    "name": "Master Warhead (Epic)",
    "type": "Module",
    "rarity": "epic",
    "energy_cost": 4,
    "attack": 0,
    "defense": 0,
    "effect_text": "Breach Cascade. Overflow Fire. Radiation Leak. Deal 18; adjacent 5; 3 radiation.",
    "keywords": [
      "breach_cascade",
      "overflow_fire",
      "radiation_leak"
    ],
    "flavor_text": "The shell engineers leave on the top rack. The top rack has the special lock.",
    "archetype": "aggro",
    "subsystem_target": null,
    "escalation": false,
    "dual_identity": false,
    "cargo": false
  },
  {
    "id": "disruption_master",
    "name": "Disruption Master",
    "type": "Module",
    "rarity": "epic",
    "energy_cost": 4,
    "attack": 0,
    "defense": 0,
    "effect_text": "Signal Jamming. Disable. Data Wipe. All enemies disabled next turn; discard 1.",
    "keywords": [
      "signal_jamming",
      "disable",
      "data_wipe"
    ],
    "flavor_text": "A loud minute on the enemy's comm. Nothing goes through. Nothing comes back.",
    "archetype": "control",
    "subsystem_target": null,
    "escalation": false,
    "dual_identity": false,
    "cargo": false
  },
  {
    "id": "stasis_lock",
    "name": "Stasis Lock",
    "type": "Module",
    "rarity": "epic",
    "energy_cost": 4,
    "attack": 0,
    "defense": 0,
    "effect_text": "Tractor Beam Hold. Disable. Apply Lock. Freeze target 3 turns; skips refresh on return.",
    "keywords": [
      "tractor_beam_hold",
      "disable",
      "apply_lock"
    ],
    "flavor_text": "A small quiet room with a large quiet lock. The target enters. Does not leave.",
    "archetype": "control",
    "subsystem_target": null,
    "escalation": false,
    "dual_identity": false,
    "cargo": false
  },
  {
    "id": "overmind_bomb",
    "name": "Overmind Bomb",
    "type": "Module",
    "rarity": "epic",
    "energy_cost": 5,
    "attack": 0,
    "defense": 0,
    "effect_text": "Breach Cascade. Overflow Fire. Phase Drive. Deal 22; adjacent 5; excess to ship.",
    "keywords": [
      "breach_cascade",
      "overflow_fire",
      "phase_drive"
    ],
    "flavor_text": "Arrives through a crack in the sensor band. The crack is not in the manual.",
    "archetype": "midrange",
    "subsystem_target": null,
    "escalation": false,
    "dual_identity": false,
    "cargo": false
  },
  {
    "id": "quantum_storm",
    "name": "Quantum Storm",
    "type": "Module",
    "rarity": "epic",
    "energy_cost": 5,
    "attack": 0,
    "defense": 0,
    "effect_text": "Phase Drive. Radiation Leak. Critical Strike. Deal 20 damage; 5 radiation over 3 turns.",
    "keywords": [
      "phase_drive",
      "radiation_leak",
      "critical_strike"
    ],
    "flavor_text": "A shell that goes through the other ship sideways. Leaves a trail inside.",
    "archetype": "aggro",
    "subsystem_target": null,
    "escalation": false,
    "dual_identity": false,
    "cargo": false
  },
  {
    "id": "master_override_e",
    "name": "Master Override (Epic)",
    "type": "Module",
    "rarity": "epic",
    "energy_cost": 5,
    "attack": 0,
    "defense": 0,
    "effect_text": "Hack/Corrupt. Transform/Overhaul. Disable. Take control of up to 2 enemy Drones.",
    "keywords": [
      "hack_corrupt",
      "transform_overhaul",
      "disable"
    ],
    "flavor_text": "Speaks two words to the enemy fleet. The fleet answers in your own colors.",
    "archetype": "control",
    "subsystem_target": null,
    "escalation": false,
    "dual_identity": false,
    "cargo": false
  },
  {
    "id": "nano_master",
    "name": "Nano Master",
    "type": "Module",
    "rarity": "epic",
    "energy_cost": 5,
    "attack": 0,
    "defense": 0,
    "effect_text": "Auto-Repair 4. Emergency Reboot. Restore 20 HP and stabilize for 2 turns.",
    "keywords": [
      "auto_repair",
      "emergency_reboot"
    ],
    "flavor_text": "Tiny careful hands across the whole hull. Every seam closes. Every pilot exhales.",
    "archetype": "ramp",
    "subsystem_target": null,
    "escalation": false,
    "dual_identity": false,
    "cargo": false
  },
  {
    "id": "reality_warp",
    "name": "Reality Warp",
    "type": "Module",
    "rarity": "epic",
    "energy_cost": 6,
    "attack": 0,
    "defense": 0,
    "effect_text": "Phase Drive. Critical Strike. Overflow Fire. Deal 25; bypasses blockers.",
    "keywords": [
      "phase_drive",
      "critical_strike",
      "overflow_fire"
    ],
    "flavor_text": "Reality blinks once. The enemy ship is somewhere that does not agree with reality anymore.",
    "archetype": "aggro",
    "subsystem_target": null,
    "escalation": false,
    "dual_identity": false,
    "cargo": false
  },
  {
    "id": "nuclear_master",
    "name": "Nuclear Master",
    "type": "Module",
    "rarity": "epic",
    "energy_cost": 6,
    "attack": 0,
    "defense": 0,
    "effect_text": "Breach Cascade. Radiation Leak. Overflow Fire. Deal 28; adjacent 7; 5 radiation.",
    "keywords": [
      "breach_cascade",
      "radiation_leak",
      "overflow_fire"
    ],
    "flavor_text": "The shell the fleet signs for in triplicate. Nobody wants the last copy.",
    "archetype": "midrange",
    "subsystem_target": null,
    "escalation": false,
    "dual_identity": false,
    "cargo": false
  },
  {
    "id": "temporal_bomb",
    "name": "Temporal Bomb",
    "type": "Module",
    "rarity": "epic",
    "energy_cost": 7,
    "attack": 0,
    "defense": 0,
    "effect_text": "Phase Drive. Radiation Leak. Breach Cascade. Deal 30; adjacent 7; 6 radiation over 3.",
    "keywords": [
      "phase_drive",
      "radiation_leak",
      "breach_cascade"
    ],
    "flavor_text": "Goes off in three different moments at once. All three moments agree on the outcome.",
    "archetype": "aggro",
    "subsystem_target": null,
    "escalation": false,
    "dual_identity": false,
    "cargo": false
  },
  {
    "id": "grand_nuke",
    "name": "Grand Nuke",
    "type": "Module",
    "rarity": "epic",
    "energy_cost": 8,
    "attack": 0,
    "defense": 0,
    "effect_text": "Priority Fire. Breach Cascade. Radiation Leak. Overflow Fire. Deal 36; adjacent 10; 7 radiation.",
    "keywords": [
      "priority_fire",
      "breach_cascade",
      "radiation_leak",
      "overflow_fire"
    ],
    "flavor_text": "The shell in the vault behind the vault. Both vaults require separate clearance.",
    "archetype": "aggro",
    "subsystem_target": null,
    "escalation": false,
    "dual_identity": false,
    "cargo": false
  },
  {
    "id": "master_priority",
    "name": "Master Priority",
    "type": "Maneuver",
    "rarity": "epic",
    "energy_cost": 3,
    "attack": 0,
    "defense": 0,
    "effect_text": "All your Weapons gain Priority Fire and Alpha Strike this turn.",
    "keywords": [
      "priority_fire",
      "alpha_strike"
    ],
    "flavor_text": "One word over the comm. Every gun on the ship doubles up and goes first.",
    "archetype": "combo",
    "subsystem_target": null,
    "escalation": false,
    "dual_identity": false,
    "cargo": false
  },
  {
    "id": "phantom_strike_e",
    "name": "Phantom Strike (Epic)",
    "type": "Maneuver",
    "rarity": "epic",
    "energy_cost": 4,
    "attack": 0,
    "defense": 0,
    "effect_text": "Phantom Echo. Gain Stealth. Create decoy of target enemy that fights for you; remain unseen.",
    "keywords": [
      "phantom_echo",
      "gain_stealth"
    ],
    "flavor_text": "Copies the enemy's best drone. Tells the copy whose side it is on.",
    "archetype": "control",
    "subsystem_target": null,
    "escalation": false,
    "dual_identity": false,
    "cargo": false
  },
  {
    "id": "chaos_warp",
    "name": "Chaos Warp",
    "type": "Maneuver",
    "rarity": "epic",
    "energy_cost": 4,
    "attack": 0,
    "defense": 0,
    "effect_text": "Transform/Overhaul. AI Takeover. Target enemy Drone becomes friendly and attacks its owner.",
    "keywords": [
      "transform_overhaul",
      "ai_takeover"
    ],
    "flavor_text": "The drone reads the new order, crosses the field, does not look back.",
    "archetype": "control",
    "subsystem_target": null,
    "escalation": false,
    "dual_identity": false,
    "cargo": false
  },
  {
    "id": "master_defense",
    "name": "Master Defense",
    "type": "Maneuver",
    "rarity": "epic",
    "energy_cost": 4,
    "attack": 0,
    "defense": 0,
    "effect_text": "Prevent all damage to your ship this turn; restore 8 HP.",
    "keywords": [],
    "flavor_text": "A small word over the comm. A large wall around the ship briefly.",
    "archetype": "control",
    "subsystem_target": null,
    "escalation": false,
    "dual_identity": false,
    "cargo": false
  },
  {
    "id": "apex_strike",
    "name": "Apex Strike",
    "type": "Maneuver",
    "rarity": "epic",
    "energy_cost": 5,
    "attack": 0,
    "defense": 0,
    "effect_text": "All your Weapons gain Critical Strike, Overclock, and Priority Fire this turn.",
    "keywords": [
      "critical_strike",
      "overclock",
      "priority_fire"
    ],
    "flavor_text": "The fleet commits. The reactor commits. The enemy commits to leaving, exactly late enough.",
    "archetype": "combo",
    "subsystem_target": null,
    "escalation": false,
    "dual_identity": false,
    "cargo": false
  },
  {
    "id": "master_warp",
    "name": "Master Warp",
    "type": "Maneuver",
    "rarity": "epic",
    "energy_cost": 5,
    "attack": 0,
    "defense": 0,
    "effect_text": "All your units gain Phase Drive and Evade 50% this turn.",
    "keywords": [
      "phase_drive",
      "evade"
    ],
    "flavor_text": "The whole fleet steps sideways for a heartbeat. Nobody lands. Nobody writes it up.",
    "archetype": "utility",
    "subsystem_target": null,
    "escalation": false,
    "dual_identity": false,
    "cargo": false
  },
  {
    "id": "total_charge",
    "name": "Total Charge",
    "type": "Maneuver",
    "rarity": "epic",
    "energy_cost": 6,
    "attack": 0,
    "defense": 0,
    "effect_text": "All your Weapons fire with Priority Fire, Alpha Strike, and Critical Strike this turn.",
    "keywords": [
      "priority_fire",
      "alpha_strike",
      "critical_strike"
    ],
    "flavor_text": "No plan. No retreat. Every weapon resolving on the same loud heartbeat. Nothing left unused.",
    "archetype": "combo",
    "subsystem_target": null,
    "escalation": false,
    "dual_identity": false,
    "cargo": false
  },
  {
    "id": "grand_defense",
    "name": "Grand Defense",
    "type": "Maneuver",
    "rarity": "epic",
    "energy_cost": 6,
    "attack": 0,
    "defense": 0,
    "effect_text": "Prevent all damage to your ship this turn; restore 5 HP to each friendly unit.",
    "keywords": [],
    "flavor_text": "The whole fleet breathes in. Nothing lands. The fleet breathes out, patched and quiet.",
    "archetype": "control",
    "subsystem_target": null,
    "escalation": false,
    "dual_identity": false,
    "cargo": false
  },
  {
    "id": "supreme_strike",
    "name": "Supreme Strike",
    "type": "Maneuver",
    "rarity": "epic",
    "energy_cost": 7,
    "attack": 0,
    "defense": 0,
    "effect_text": "All your Weapons and Drones attack with Priority Fire, Alpha Strike, Critical Strike.",
    "keywords": [
      "priority_fire",
      "alpha_strike",
      "critical_strike"
    ],
    "flavor_text": "The fleet strikes once. The fleet strikes twice. The enemy does not strike anything back.",
    "archetype": "combo",
    "subsystem_target": null,
    "escalation": false,
    "dual_identity": false,
    "cargo": false
  },
  {
    "id": "master_scope_e",
    "name": "Master Scope (Epic)",
    "type": "Equipment",
    "rarity": "epic",
    "energy_cost": 3,
    "attack": 0,
    "defense": 0,
    "effect_text": "Attach to a Weapon. Host gains Priority Fire, Critical Strike, Tracking Lock, Alpha Strike.",
    "keywords": [
      "priority_fire",
      "critical_strike",
      "tracking_lock",
      "alpha_strike"
    ],
    "flavor_text": "Four lenses. Four opinions. One very calm pilot on the trigger, agreeing with all.",
    "archetype": "combo",
    "subsystem_target": null,
    "escalation": false,
    "dual_identity": false,
    "cargo": false
  },
  {
    "id": "elite_cloak",
    "name": "Elite Cloak",
    "type": "Equipment",
    "rarity": "epic",
    "energy_cost": 4,
    "attack": 0,
    "defense": 0,
    "effect_text": "Attach to a Drone. Host gains Gain Stealth, Cloaked Entry, Evade 50%, Phase Drive.",
    "keywords": [
      "gain_stealth",
      "cloaked_entry",
      "evade",
      "phase_drive"
    ],
    "flavor_text": "The cloak the drone wears to work. The drone never takes it off.",
    "archetype": "utility",
    "subsystem_target": null,
    "escalation": false,
    "dual_identity": false,
    "cargo": false
  },
  {
    "id": "master_plating",
    "name": "Master Plating",
    "type": "Equipment",
    "rarity": "epic",
    "energy_cost": 4,
    "attack": 0,
    "defense": 0,
    "effect_text": "Attach to a Drone. Host gains +8 defense, Reinforced Hull, Ablative Plating, Auto-Repair.",
    "keywords": [
      "reinforced_hull",
      "ablative_plating",
      "auto_repair"
    ],
    "flavor_text": "Thicker, stubborner, quieter. The drone wears it like it was born into it, eventually.",
    "archetype": "midrange",
    "subsystem_target": null,
    "escalation": false,
    "dual_identity": false,
    "cargo": false
  },
  {
    "id": "fleet_network",
    "name": "Fleet Network",
    "type": "Equipment",
    "rarity": "epic",
    "energy_cost": 5,
    "attack": 0,
    "defense": 0,
    "effect_text": "Attach to your ship. Your ship gains Crew Pooling, Cascading Power, Efficiency Protocol.",
    "keywords": [
      "crew_pooling",
      "cascading_power",
      "efficiency_protocol"
    ],
    "flavor_text": "One wire down the spine of the fleet. Every ship reads the same quiet heartbeat.",
    "archetype": "ramp",
    "subsystem_target": null,
    "escalation": false,
    "dual_identity": false,
    "cargo": false
  },
  {
    "id": "supreme_targeting",
    "name": "Supreme Targeting",
    "type": "Equipment",
    "rarity": "epic",
    "energy_cost": 5,
    "attack": 0,
    "defense": 0,
    "effect_text": "Attach to a Weapon. Host gains Priority Fire, Critical Strike, Alpha Strike, Tracking Lock.",
    "keywords": [
      "priority_fire",
      "critical_strike",
      "alpha_strike",
      "tracking_lock"
    ],
    "flavor_text": "Four names on the target's ticket. Four ways the ticket gets punched, first.",
    "archetype": "combo",
    "subsystem_target": null,
    "escalation": false,
    "dual_identity": false,
    "cargo": false
  },
  {
    "id": "phantom_rig",
    "name": "Phantom Rig",
    "type": "Equipment",
    "rarity": "epic",
    "energy_cost": 5,
    "attack": 0,
    "defense": 0,
    "effect_text": "Attach to a Drone. Host gains Gain Stealth, Cloaked Entry, Phase Drive, Evade 50%.",
    "keywords": [
      "gain_stealth",
      "cloaked_entry",
      "phase_drive",
      "evade"
    ],
    "flavor_text": "The drone puts this on for work. The work happens. Nobody writes up the drone.",
    "archetype": "utility",
    "subsystem_target": null,
    "escalation": false,
    "dual_identity": false,
    "cargo": false
  },
  {
    "id": "apex_armor",
    "name": "Apex Armor",
    "type": "Equipment",
    "rarity": "epic",
    "energy_cost": 6,
    "attack": 0,
    "defense": 0,
    "effect_text": "Attach to a Drone. Host gains +8 defense, Reinforced Hull, Ablative Plating, Auto-Repair.",
    "keywords": [
      "reinforced_hull",
      "ablative_plating",
      "auto_repair"
    ],
    "flavor_text": "Worn by the drone that comes back. Always comes back. The fleet never asks why.",
    "archetype": "midrange",
    "subsystem_target": null,
    "escalation": false,
    "dual_identity": false,
    "cargo": false
  },
  {
    "id": "grand_uplink",
    "name": "Grand Uplink",
    "type": "Equipment",
    "rarity": "epic",
    "energy_cost": 6,
    "attack": 0,
    "defense": 0,
    "effect_text": "Attach to your ship. Your units gain Priority Fire, Rapid Launch, Cascading Power.",
    "keywords": [
      "priority_fire",
      "rapid_launch",
      "cascading_power"
    ],
    "flavor_text": "One wire into every ship at once. One heartbeat. One quiet sentence. The fleet moves.",
    "archetype": "aggro",
    "subsystem_target": null,
    "escalation": false,
    "dual_identity": false,
    "cargo": false
  },
  {
    "id": "apex_zone",
    "name": "Apex Zone",
    "type": "Field",
    "rarity": "epic",
    "energy_cost": 4,
    "attack": 0,
    "defense": 0,
    "effect_text": "Environmental. All units gain Priority Fire and Rapid Launch. Replaces any active Environmental.",
    "keywords": [
      "persistent_field",
      "priority_fire",
      "rapid_launch"
    ],
    "flavor_text": "A region of fast decisions. Every pilot inside learns to answer before being asked.",
    "archetype": "aggro",
    "subsystem_target": null,
    "escalation": false,
    "dual_identity": false,
    "cargo": false
  },
  {
    "id": "chaos_storm",
    "name": "Chaos Storm",
    "type": "Field",
    "rarity": "epic",
    "energy_cost": 5,
    "attack": 0,
    "defense": 0,
    "effect_text": "Environmental. Breach Cascade effects trigger twice; Radiation Leak lasts +1 turn. Replaces.",
    "keywords": [
      "persistent_field",
      "breach_cascade",
      "radiation_leak"
    ],
    "flavor_text": "A region where nothing small stays small. Every fire feeds the next fire by invitation.",
    "archetype": "aggro",
    "subsystem_target": null,
    "escalation": false,
    "dual_identity": false,
    "cargo": false
  },
  {
    "id": "phase_region",
    "name": "Phase Region",
    "type": "Field",
    "rarity": "epic",
    "energy_cost": 5,
    "attack": 0,
    "defense": 0,
    "effect_text": "Environmental. All units gain Phase Drive and Gain Stealth. Replaces any active Environmental.",
    "keywords": [
      "persistent_field",
      "phase_drive",
      "gain_stealth"
    ],
    "flavor_text": "A region where existing is a suggestion. The ships inside take it seriously.",
    "archetype": "utility",
    "subsystem_target": null,
    "escalation": false,
    "dual_identity": false,
    "cargo": false
  },
  {
    "id": "fortress_region",
    "name": "Fortress Region",
    "type": "Field",
    "rarity": "epic",
    "energy_cost": 5,
    "attack": 0,
    "defense": 0,
    "effect_text": "Environmental. All Defense units gain Interceptor, Ablative Plating, Auto-Repair. Replaces.",
    "keywords": [
      "persistent_field",
      "interceptor",
      "ablative_plating",
      "auto_repair"
    ],
    "flavor_text": "Every wall in the region finds a second wind. Every wall keeps standing.",
    "archetype": "midrange",
    "subsystem_target": null,
    "escalation": false,
    "dual_identity": false,
    "cargo": false
  },
  {
    "id": "supreme_battleground",
    "name": "Supreme Battleground",
    "type": "Field",
    "rarity": "epic",
    "energy_cost": 6,
    "attack": 0,
    "defense": 0,
    "effect_text": "Environmental. All units gain Priority Fire and Alpha Strike. Replaces any active Environmental.",
    "keywords": [
      "persistent_field",
      "priority_fire",
      "alpha_strike"
    ],
    "flavor_text": "Every gun finishes the sentence first. Every gun has the second sentence ready.",
    "archetype": "combo",
    "subsystem_target": null,
    "escalation": false,
    "dual_identity": false,
    "cargo": false
  },
  {
    "id": "chrono_field",
    "name": "Chrono Field",
    "type": "Field",
    "rarity": "epic",
    "energy_cost": 7,
    "attack": 0,
    "defense": 0,
    "effect_text": "Environmental. Deferred Deployment. Reactive. Phase Drive. Replaces any active Environmental.",
    "keywords": [
      "persistent_field",
      "deferred_deployment",
      "reactive",
      "phase_drive"
    ],
    "flavor_text": "Time waits politely for the fleet. The fleet uses the wait to finish sentences.",
    "archetype": "utility",
    "subsystem_target": null,
    "escalation": false,
    "dual_identity": false,
    "cargo": true
  },
  {
    "id": "elite_fighter_core",
    "name": "Elite Fighter Core",
    "type": "Ship Core",
    "rarity": "epic",
    "energy_cost": 0,
    "attack": 0,
    "defense": 0,
    "effect_text": "Passive: Your first Weapon each turn has Priority Fire and costs 1 less.",
    "keywords": [],
    "flavor_text": "The core every elite squadron has under the floor panel. The panel never lists it.",
    "archetype": "aggro",
    "subsystem_target": null,
    "escalation": false,
    "dual_identity": false,
    "cargo": false
  },
  {
    "id": "sniper_mount",
    "name": "Sniper Mount",
    "type": "Equipment",
    "rarity": "uncommon",
    "energy_cost": 2,
    "attack": 0,
    "defense": 0,
    "effect_text": "Attach to a Weapon. Host gains Critical Strike and Priority Fire.",
    "keywords": [
      "critical_strike",
      "priority_fire"
    ],
    "flavor_text": "Long tube. Long patience. A pilot who agreed to both on the first afternoon.",
    "archetype": "combo",
    "subsystem_target": null,
    "escalation": false,
    "dual_identity": false,
    "cargo": false
  },
  {
    "id": "stabilizer_plate",
    "name": "Stabilizer Plate",
    "type": "Equipment",
    "rarity": "uncommon",
    "energy_cost": 2,
    "attack": 0,
    "defense": 0,
    "effect_text": "Attach to a Drone. Host gains Reinforced Hull and Auto-Repair 1.",
    "keywords": [
      "reinforced_hull",
      "auto_repair"
    ],
    "flavor_text": "A quiet weight under the drone's ribs. The drone flies with more confidence.",
    "archetype": "midrange",
    "subsystem_target": null,
    "escalation": false,
    "dual_identity": false,
    "cargo": false
  },
  {
    "id": "phase_rig",
    "name": "Phase Rig",
    "type": "Equipment",
    "rarity": "uncommon",
    "energy_cost": 3,
    "attack": 0,
    "defense": 0,
    "effect_text": "Attach to your ship. Your ship gains Phase Drive and Gain Stealth for 2 turns.",
    "keywords": [
      "phase_drive",
      "gain_stealth"
    ],
    "flavor_text": "Two drawers on the console. Both drawers open at once. The ship steps out quietly.",
    "archetype": "utility",
    "subsystem_target": null,
    "escalation": false,
    "dual_identity": false,
    "cargo": false
  },
  {
    "id": "battle_harness",
    "name": "Battle Harness",
    "type": "Equipment",
    "rarity": "uncommon",
    "energy_cost": 3,
    "attack": 0,
    "defense": 0,
    "effect_text": "Attach to a Drone. Host gains Battle Hardened and Rapid Launch.",
    "keywords": [
      "battle_hardened",
      "rapid_launch"
    ],
    "flavor_text": "The drone wears the harness to work. The work is loud. The harness is louder.",
    "archetype": "aggro",
    "subsystem_target": null,
    "escalation": false,
    "dual_identity": false,
    "cargo": false
  },
  {
    "id": "energy_matrix",
    "name": "Energy Matrix",
    "type": "Equipment",
    "rarity": "uncommon",
    "energy_cost": 3,
    "attack": 0,
    "defense": 0,
    "effect_text": "Attach to your ship. Your ship gains Overclock and Efficiency Protocol.",
    "keywords": [
      "overclock",
      "efficiency_protocol"
    ],
    "flavor_text": "Runs the reactor a little hot. Runs the ledger a little cold. Both end even.",
    "archetype": "ramp",
    "subsystem_target": null,
    "escalation": false,
    "dual_identity": false,
    "cargo": false
  },
  {
    "id": "fleet_formation",
    "name": "Fleet Formation",
    "type": "Field",
    "rarity": "uncommon",
    "energy_cost": 2,
    "attack": 0,
    "defense": 0,
    "effect_text": "Persistent Field. Your Drones gain +1/+1 while this is in play.",
    "keywords": [
      "persistent_field"
    ],
    "flavor_text": "Every wingman reads the same heartbeat. Every wingman slots into the correct bracket.",
    "archetype": "aggro",
    "subsystem_target": null,
    "escalation": false,
    "dual_identity": false,
    "cargo": false
  },
  {
    "id": "targeting_field",
    "name": "Targeting Field",
    "type": "Field",
    "rarity": "uncommon",
    "energy_cost": 3,
    "attack": 0,
    "defense": 0,
    "effect_text": "Persistent Field. Your Weapons gain Priority Fire while this is in play.",
    "keywords": [
      "persistent_field",
      "priority_fire"
    ],
    "flavor_text": "A grid across the sky. Every gun under it finds a faster trigger this afternoon.",
    "archetype": "combo",
    "subsystem_target": null,
    "escalation": false,
    "dual_identity": false,
    "cargo": false
  },
  {
    "id": "recon_region",
    "name": "Recon Region",
    "type": "Field",
    "rarity": "uncommon",
    "energy_cost": 3,
    "attack": 0,
    "defense": 0,
    "effect_text": "Persistent Field. End Cycle: Probe 1.",
    "keywords": [
      "persistent_field",
      "probe"
    ],
    "flavor_text": "A region watched by small invisible eyes. The eyes write a short note each evening.",
    "archetype": "utility",
    "subsystem_target": null,
    "escalation": false,
    "dual_identity": false,
    "cargo": false
  },
  {
    "id": "master_conduit",
    "name": "Master Conduit",
    "type": "Equipment",
    "rarity": "rare",
    "energy_cost": 4,
    "attack": 0,
    "defense": 0,
    "effect_text": "Attach to your ship. Your ship gains Crew Pooling, Cascading Power, Efficiency Protocol.",
    "keywords": [
      "crew_pooling",
      "cascading_power",
      "efficiency_protocol"
    ],
    "flavor_text": "One wire through the fleet. Every ship finds its quiet twin on the other end.",
    "archetype": "ramp",
    "subsystem_target": null,
    "escalation": false,
    "dual_identity": false,
    "cargo": false
  },
  {
    "id": "stealth_region",
    "name": "Stealth Region",
    "type": "Field",
    "rarity": "rare",
    "energy_cost": 5,
    "attack": 0,
    "defense": 0,
    "effect_text": "Environmental. All units gain Gain Stealth and Cloaked Entry. Replaces.",
    "keywords": [
      "persistent_field",
      "gain_stealth",
      "cloaked_entry"
    ],
    "flavor_text": "Every ship in the region becomes a rumor. The enemy files the rumor, keeps firing.",
    "archetype": "control",
    "subsystem_target": null,
    "escalation": false,
    "dual_identity": false,
    "cargo": false
  }
]
